README.md
setup.py
udac_probability/Binomialdistribution.py
udac_probability/Gaussiandistribution.py
udac_probability/Generaldistribution.py
udac_probability/__init__.py
udac_probability.egg-info/PKG-INFO
udac_probability.egg-info/SOURCES.txt
udac_probability.egg-info/dependency_links.txt
udac_probability.egg-info/not-zip-safe
udac_probability.egg-info/top_level.txt