Metadata-Version: 1.0
Name: udac-probability
Version: 0.1
Summary: Gaussian and Binomial distributions
Home-page: UNKNOWN
Author: Chidimma Dominic Nweke
Author-email: realchidinweke@gmail.com
License: UNKNOWN
Platform: UNKNOWN
